morris/test_morris.py
morris/__init__.py
morris-1.2.dist-info/WHEEL
morris-1.2.dist-info/zip-safe
morris-1.2.dist-info/DESCRIPTION.rst
morris-1.2.dist-info/RECORD
morris-1.2.dist-info/metadata.json
morris-1.2.dist-info/METADATA
morris-1.2.dist-info/top_level.txt
