Metadata-Version: 1.1
Name: morris
Version: 1.2
Summary: Morris is an announcement (signal/event) system for Python
Home-page: https://github.com/zyga/morris
Author: Zygmunt Krynicki
Author-email: me@zygoon.pl
License: LGPLv3
Keywords: morris signal event pub/sub
Platform: UNKNOWN
Classifier: Development Status :: 5 - Production/Stable
Classifier: Intended Audience :: Developers
Classifier: License :: OSI Approved :: GNU Lesser General Public License v3 (LGPLv3)
Classifier: Natural Language :: English
Classifier: Programming Language :: Python :: 2
Classifier: Programming Language :: Python :: 2.7
Classifier: Programming Language :: Python :: 3
Classifier: Programming Language :: Python :: 3.2
Classifier: Programming Language :: Python :: 3.3
Classifier: Programming Language :: Python :: 3.4
Classifier: Programming Language :: Python :: Implementation :: CPython
Classifier: Programming Language :: Python :: Implementation :: PyPy
